{
  "name": "Test",
  "race": "Unknown",
  "steps": [
    {
      "supply": 12,
      "time": "0:00",
      "action": "SCV"
    },
    {
      "supply": 14,
      "time": "0:02",
      "action": "Supply Depot"
    },
    {
      "supply": 16,
      "time": "0:04",
      "action": "Barracks"
    },
    {
      "supply": 16,
      "time": "0:06",
      "action": "Refinery"
    },
    {
      "supply": 19,
      "time": "0:08",
      "action": "Orbital Command"
    },
    {
      "supply": 19,
      "time": "0:10",
      "action": "Barracks Reactor"
    },
    {
      "supply": 19,
      "time": "1:42",
      "action": "Command Center"
    },
    {
      "supply": 20,
      "time": "1:58",
      "action": "Supply Depot"
    },
    {
      "supply": 21,
      "time": "2:10",
      "action": "Barracks x2"
    },
    {
      "supply": 30,
      "time": "2:52",
      "action": "Orbital Command"
    },
    {
      "supply": 30,
      "time": "2:55",
      "action": "Barracks Tech Lab x2"
    },
    {
      "supply": 35,
      "time": "3:22",
      "action": "Stimpack"
    },
    {
      "supply": 42,
      "time": "3:46",
      "action": "Combat Shield"
    },
    {
      "supply": 40,
      "time": "3:33",
      "action": "Supply Depot"
    },
    {
      "supply": 62,
      "time": "4:46",
      "action": "Factory"
    },
    {
      "supply": 62,
      "time": "4:47",
      "action": "Engineering Bay"
    },
    {
      "supply": 74,
      "time": "5:20",
      "action": "Refinery x3"
    },
    {
      "supply": 74,
      "time": "5:21",
      "action": "Terran Infantry Weapons Level 1"
    },
    {
      "supply": 76,
      "time": "5:30",
      "action": "Action"
    },
    {
      "supply": 76,
      "time": "5:31",
      "action": "Barracks x2"
    },
    {
      "supply": 87,
      "time": "5:55",
      "action": "Factory Reactor"
    },
    {
      "supply": 87,
      "time": "5:56",
      "action": "Starport"
    },
    {
      "supply": 93,
      "time": "6:35",
      "action": "Factory Tech Lab"
    },
    {
      "supply": 130,
      "time": "7:15",
      "action": "Terran Infantry Armor Level 1"
    },
    {
      "supply": 166,
      "time": "8:00",
      "action": "Action"
    }
  ]
}