{
  "name": "PiG's Beginner Terran 1-1-1 (Silver, 2023) (TvX Timing Attack)",
  "race": "Unknown",
  "steps": [
    {
      "supply": 14,
      "time": "0:17",
      "action": "Supply Depot"
    },
    {
      "supply": 16,
      "time": "0:40",
      "action": "Barracks"
    },
    {
      "supply": 16,
      "time": "0:44",
      "action": "Refinery"
    },
    {
      "supply": 19,
      "time": "1:29",
      "action": "Barracks Reactor, Orbital Command"
    },
    {
      "supply": 19,
      "time": "1:44",
      "action": "Command Center"
    },
    {
      "supply": 20,
      "time": "2:00",
      "action": "Supply Depot"
    },
    {
      "supply": 21,
      "time": "2:11",
      "action": "Marine x2"
    },
    {
      "supply": 21,
      "time": "2:18",
      "action": "Factory"
    },
    {
      "supply": 22,
      "time": "2:26",
      "action": "Refinery"
    },
    {
      "supply": 23,
      "time": "2:44",
      "action": "Bunker"
    },
    {
      "supply": 30,
      "time": "2:58",
      "action": "Orbital Command"
    },
    {
      "supply": 31,
      "time": "3:10",
      "action": "Starport, Factory Tech Lab"
    },
    {
      "supply": 42,
      "time": "3:38",
      "action": "Siege Tank"
    },
    {
      "supply": 42,
      "time": "3:44",
      "action": "Supply Depot"
    },
    {
      "supply": 46,
      "time": "4:05",
      "action": "Viking"
    },
    {
      "supply": 52,
      "time": "4:33",
      "action": "Barracks"
    },
    {
      "supply": 53,
      "time": "4:36",
      "action": "Barracks"
    },
    {
      "supply": 53,
      "time": "4:38",
      "action": "Barracks"
    },
    {
      "supply": 53,
      "time": "4:39",
      "action": "Barracks"
    },
    {
      "supply": 60,
      "time": "4:56",
      "action": "Starport Reactor"
    },
    {
      "supply": 62,
      "time": "5:27",
      "action": "Refinery x2"
    },
    {
      "supply": 64,
      "time": "5:29",
      "action": "Engineering Bay"
    },
    {
      "supply": 64,
      "time": "5:33",
      "action": "Barracks Tech Lab x2"
    },
    {
      "supply": 64,
      "time": "5:34",
      "action": "Barracks Reactor x2"
    },
    {
      "supply": 73,
      "time": "5:52",
      "action": "Stimpack"
    },
    {
      "supply": 75,
      "time": "5:54",
      "action": "Combat Shield"
    },
    {
      "supply": 76,
      "time": "6:10",
      "action": "Terran Infantry Weapons Level 1"
    },
    {
      "supply": 95,
      "time": "6:48",
      "action": "Concussive Shells"
    }
  ]
}